{
  "asOf": "2026-04-15 15:06 UTC",
  "us": [
    {
      "ticker": "^IRX",
      "name": "3-Month T-Bill",
      "maturity": "3M",
      "price": 3.618,
      "change1d": 0.17,
      "change1w": 0.5,
      "high52": 4.305,
      "low52": 3.507
    },
    {
      "ticker": "^FVX",
      "name": "5-Year T-Note",
      "maturity": "5Y",
      "price": 3.894,
      "change1d": 0.59,
      "change1w": -0.66,
      "high52": 4.17,
      "low52": 3.507
    },
    {
      "ticker": "^TNX",
      "name": "10-Year T-Note",
      "maturity": "10Y",
      "price": 4.275,
      "change1d": 0.45,
      "change1w": -0.37,
      "high52": 4.629,
      "low52": 3.947
    },
    {
      "ticker": "^TYX",
      "name": "30-Year T-Bond",
      "maturity": "30Y",
      "price": 4.884,
      "change1d": 0.33,
      "change1w": -0.06,
      "high52": 5.153,
      "low52": 4.528
    }
  ],
  "international": [
    {
      "ticker": "IGOV",
      "name": "Developed Markets Govt Bonds",
      "region": "Global DM",
      "price": 42.04,
      "change1d": 0.14,
      "change1w": 0.86,
      "high52": 43.12,
      "low52": 39.8181
    },
    {
      "ticker": "BWX",
      "name": "Intl Treasury Bond",
      "region": "Global DM",
      "price": 22.335,
      "change1d": -0.2,
      "change1w": 0.38,
      "high52": 23.148,
      "low52": 21.6056
    },
    {
      "ticker": "BNDX",
      "name": "Total Intl Bond (Hedged)",
      "region": "Global",
      "price": 48.1443,
      "change1d": -0.16,
      "change1w": -0.28,
      "high52": 49.0154,
      "low52": 46.812
    },
    {
      "ticker": "EMB",
      "name": "EM USD Sovereign Debt",
      "region": "Emerging Markets",
      "price": 96.29,
      "change1d": -0.18,
      "change1w": 1.24,
      "high52": 96.9249,
      "low52": 83.1659
    },
    {
      "ticker": "EMLC",
      "name": "EM Local Currency Bonds",
      "region": "Emerging Markets",
      "price": 25.97,
      "change1d": -0.08,
      "change1w": 1.09,
      "high52": 26.361,
      "low52": 22.4595
    }
  ],
  "corporate": [
    {
      "ticker": "LQD",
      "name": "US Investment Grade Corp",
      "type": "IG Corp",
      "price": 109.87,
      "change1d": -0.1,
      "change1w": 0.35,
      "high52": 111.0897,
      "low52": 100.8585
    },
    {
      "ticker": "HYG",
      "name": "US High Yield Corp",
      "type": "HY Corp",
      "price": 80.435,
      "change1d": -0.08,
      "change1w": 0.31,
      "high52": 80.56,
      "low52": 72.7525
    },
    {
      "ticker": "JNK",
      "name": "US High Yield (alt)",
      "type": "HY Corp",
      "price": 96.79,
      "change1d": -0.08,
      "change1w": 0.32,
      "high52": 96.97,
      "low52": 86.9819
    },
    {
      "ticker": "VCIT",
      "name": "Vanguard Corp Bond Interm",
      "type": "IG Corp",
      "price": 83.325,
      "change1d": -0.13,
      "change1w": 0.36,
      "high52": 84.1851,
      "low52": 76.4537
    }
  ]
}